odoo8_addon_account_invoice_shipping_address-8.0.0.1.1.99.dev21-py2.7-nspkg.pth
odoo8_addon_account_invoice_shipping_address-8.0.0.1.1.99.dev21.dist-info/METADATA
odoo8_addon_account_invoice_shipping_address-8.0.0.1.1.99.dev21.dist-info/RECORD
odoo8_addon_account_invoice_shipping_address-8.0.0.1.1.99.dev21.dist-info/WHEEL
odoo8_addon_account_invoice_shipping_address-8.0.0.1.1.99.dev21.dist-info/namespace_packages.txt
odoo8_addon_account_invoice_shipping_address-8.0.0.1.1.99.dev21.dist-info/top_level.txt
odoo_addons/account_invoice_shipping_address/README.rst
odoo_addons/account_invoice_shipping_address/__init__.py
odoo_addons/account_invoice_shipping_address/__openerp__.py
odoo_addons/account_invoice_shipping_address/invoice.py
odoo_addons/account_invoice_shipping_address/invoice_view.xml
odoo_addons/account_invoice_shipping_address/sale.py
odoo_addons/account_invoice_shipping_address/stock.py
odoo_addons/account_invoice_shipping_address/i18n/ar.po
odoo_addons/account_invoice_shipping_address/i18n/bg.po
odoo_addons/account_invoice_shipping_address/i18n/bs.po
odoo_addons/account_invoice_shipping_address/i18n/ca.po
odoo_addons/account_invoice_shipping_address/i18n/cs.po
odoo_addons/account_invoice_shipping_address/i18n/de.po
odoo_addons/account_invoice_shipping_address/i18n/el_GR.po
odoo_addons/account_invoice_shipping_address/i18n/en_GB.po
odoo_addons/account_invoice_shipping_address/i18n/es.po
odoo_addons/account_invoice_shipping_address/i18n/es_AR.po
odoo_addons/account_invoice_shipping_address/i18n/es_CR.po
odoo_addons/account_invoice_shipping_address/i18n/es_EC.po
odoo_addons/account_invoice_shipping_address/i18n/es_MX.po
odoo_addons/account_invoice_shipping_address/i18n/es_PE.po
odoo_addons/account_invoice_shipping_address/i18n/et.po
odoo_addons/account_invoice_shipping_address/i18n/fi.po
odoo_addons/account_invoice_shipping_address/i18n/fr.po
odoo_addons/account_invoice_shipping_address/i18n/fr_CA.po
odoo_addons/account_invoice_shipping_address/i18n/fr_CH.po
odoo_addons/account_invoice_shipping_address/i18n/gl.po
odoo_addons/account_invoice_shipping_address/i18n/hr.po
odoo_addons/account_invoice_shipping_address/i18n/hr_HR.po
odoo_addons/account_invoice_shipping_address/i18n/hu.po
odoo_addons/account_invoice_shipping_address/i18n/id.po
odoo_addons/account_invoice_shipping_address/i18n/it.po
odoo_addons/account_invoice_shipping_address/i18n/ja.po
