Metadata-Version: 2.1
Name: odoo8-addon-account-invoice-shipping-address
Version: 8.0.0.1.1.99.dev21
Summary: Adds a shipping address field to the invoice.
Home-page: http://www.andreacometa.it
Author: Andrea Cometa, Agile Business Group,Odoo Community Association (OCA)
Author-email: support@odoo-community.org
License: AGPL-3
Platform: UNKNOWN
Classifier: Programming Language :: Python
Classifier: Framework :: Odoo
Classifier: License :: OSI Approved :: GNU Affero General Public License v3
Requires-Python: ~=2.7
Requires-Dist: odoo (<9.0a,>=8.0a)
